a313/__init__.py
a313/a313_data.json
a313/client.py
a313-0.1.0.dist-info/METADATA
a313-0.1.0.dist-info/WHEEL
a313-0.1.0.dist-info/top_level.txt
a313-0.1.0.dist-info/RECORD
