Metadata-Version: 2.4
Name: a313
Version: 0.1.0
Summary: مكتبة بايثون لجلب الأذكار بالترتيب من قائمة محلية.
Author: tofey
License: MIT
Requires-Python: >=3.8
Dynamic: author
Dynamic: license
Dynamic: requires-python
Dynamic: summary
